{
  "updated": "2026-06-18T13:22:55",
  "cameras": {
    "Cam_231_Counter": {
      "customers_total": 1,
      "line_in": 0,
      "line_out": 0,
      "peak": 4,
      "standing": 0,
      "sitting": 0,
      "groups": 0,
      "queue": 0,
      "bags": 0,
      "persons": 0,
      "zone_current": {},
      "zone_enter_total": {},
      "hourly": {
        "13:00": 1
      },
      "alerts": [
        "[13:22:19] 排队告警 3人",
        "[13:21:39] [跨区顾客] 跨摄像头识别 1人"
      ],
      "fps": 4.5,
      "stream_online": true,
      "plus": {
        "funnel": {
          "浏览": 4,
          "完整动线": 0
        },
        "dwell_tiers": {
          "浏览": 4,
          "兴趣": 0,
          "意向": 0
        },
        "density": 0.0,
        "forecast_next_hour": 1,
        "staff_count": 0,
        "suspicious": 0,
        "cross_cam": [],
        "conversion_pct": 0.0,
        "family_groups": 0,
        "falls": 0,
        "zigzag": 0,
        "shelf_engagement": 0,
        "behaviors": {
          "browse_shelf": 7,
          "walk_fast": 1,
          "put_back": 1
        },
        "attribution": [],
        "forecast_rest_day": 7
      }
    },
    "Cam_104_Specialty": {
      "customers_total": 4,
      "line_in": 0,
      "line_out": 0,
      "peak": 3,
      "standing": 0,
      "sitting": 0,
      "groups": 0,
      "queue": 0,
      "bags": 0,
      "persons": 0,
      "zone_current": {},
      "zone_enter_total": {
        "体验区": 2,
        "货架区": 3
      },
      "hourly": {
        "13:00": 4
      },
      "alerts": [
        "[13:21:40] [跨区顾客] 跨摄像头识别 1人"
      ],
      "fps": 4.3,
      "stream_online": true,
      "plus": {
        "funnel": {
          "浏览": 4,
          "完整动线": 0
        },
        "dwell_tiers": {
          "浏览": 4,
          "兴趣": 0,
          "意向": 0
        },
        "density": 0.0,
        "forecast_next_hour": 4,
        "staff_count": 0,
        "suspicious": 0,
        "cross_cam": [],
        "conversion_pct": 0.0,
        "family_groups": 0,
        "falls": 0,
        "zigzag": 0,
        "shelf_engagement": 0,
        "behaviors": {
          "browse_shelf": 7,
          "walk_fast": 1,
          "put_back": 1
        },
        "attribution": [],
        "forecast_rest_day": 28
      }
    }
  },
  "global": {
    "store_name": "我的店铺",
    "funnel": {
      "浏览": 4,
      "完整动线": 0
    },
    "dwell_tiers": {
      "浏览": 4,
      "兴趣": 0,
      "意向": 0
    },
    "store_area_sqm": 120,
    "conversion_pct": 0.0,
    "family_groups": 0,
    "falls": 0,
    "zigzag": 0,
    "behaviors": {
      "browse_shelf": 7,
      "walk_fast": 1,
      "put_back": 1
    },
    "attribution": {
      "insights": [],
      "samples": 30
    },
    "features": {
      "boss_all_in": true,
      "funnel": true,
      "reid": true,
      "deep_reid": true,
      "events": true,
      "forecast": true,
      "fall": true,
      "family": true,
      "zigzag": true,
      "webhook": false,
      "vlm": true,
      "open_vocab": false,
      "ocr": true,
      "event_clips": false,
      "digital_twin": true,
      "multiview": true,
      "multistore": true,
      "face_blur": true,
      "active_learning": false
    }
  },
  "vlm": {
    "ts": "2026-06-18T13:21:58",
    "insight": "我的店铺 场景快照：当前 1 人，排队 0，进店累计相关指标正常。近期告警：[13:21:39] [跨区顾客] 跨摄像头识别 1人"
  },
  "clips": [
    {
      "path": "/Users/james/Project/jiance/store/analytics_logs/clips/Cam_231_Counter_20260618_131714__转化率低__转化率仅11__优化动线.mp4",
      "cam": "Cam_231_Counter",
      "message": "[转化率低] 转化率仅11% 优化动线",
      "ts": "2026-06-18T13:17:15"
    },
    {
      "path": "/Users/james/Project/jiance/store/analytics_logs/clips/Cam_231_Counter_20260618_122151__可疑停留__可疑行为_1起.mp4",
      "cam": "Cam_231_Counter",
      "message": "[可疑停留] 可疑行为 1起",
      "ts": "2026-06-18T12:21:52"
    },
    {
      "path": "/Users/james/Project/jiance/store/analytics_logs/clips/Cam_231_Counter_20260618_122153__可疑停留__可疑行为_1起.mp4",
      "cam": "Cam_231_Counter",
      "message": "[可疑停留] 可疑行为 1起",
      "ts": "2026-06-18T12:21:54"
    },
    {
      "path": "/Users/james/Project/jiance/store/analytics_logs/clips/Cam_104_Specialty_20260618_122150__可疑停留__可疑行为_1起.mp4",
      "cam": "Cam_104_Specialty",
      "message": "[可疑停留] 可疑行为 1起",
      "ts": "2026-06-18T12:21:51"
    },
    {
      "path": "/Users/james/Project/jiance/store/analytics_logs/clips/Cam_104_Specialty_20260618_122100__跨区顾客__跨摄像头识别_1人.mp4",
      "cam": "Cam_104_Specialty",
      "message": "[跨区顾客] 跨摄像头识别 1人",
      "ts": "2026-06-18T12:21:00"
    },
    {
      "path": "/Users/james/Project/jiance/store/analytics_logs/clips/Cam_231_Counter_20260618_122156__可疑停留__可疑行为_1起.mp4",
      "cam": "Cam_231_Counter",
      "message": "[可疑停留] 可疑行为 1起",
      "ts": "2026-06-18T12:21:57"
    },
    {
      "path": "/Users/james/Project/jiance/store/analytics_logs/clips/Cam_104_Specialty_20260618_122152__可疑停留__可疑行为_1起.mp4",
      "cam": "Cam_104_Specialty",
      "message": "[可疑停留] 可疑行为 1起",
      "ts": "2026-06-18T12:21:53"
    },
    {
      "path": "/Users/james/Project/jiance/store/analytics_logs/clips/Cam_231_Counter_20260618_122158__可疑停留__可疑行为_1起.mp4",
      "cam": "Cam_231_Counter",
      "message": "[可疑停留] 可疑行为 1起",
      "ts": "2026-06-18T12:21:59"
    },
    {
      "path": "/Users/james/Project/jiance/store/analytics_logs/clips/Cam_104_Specialty_20260618_122322__可疑停留__可疑行为_1起.mp4",
      "cam": "Cam_104_Specialty",
      "message": "[可疑停留] 可疑行为 1起",
      "ts": "2026-06-18T12:23:23"
    },
    {
      "path": "/Users/james/Project/jiance/store/analytics_logs/clips/Cam_104_Specialty_20260618_122154__可疑停留__可疑行为_1起.mp4",
      "cam": "Cam_104_Specialty",
      "message": "[可疑停留] 可疑行为 1起",
      "ts": "2026-06-18T12:21:55"
    }
  ],
  "twin": {
    "store": "我的店铺",
    "area_sqm": 120,
    "grid": [
      24,
      16
    ],
    "hotspots": [
      {
        "x": 11,
        "y": 4,
        "heat": 4.78
      },
      {
        "x": 9,
        "y": 6,
        "heat": 6.43
      },
      {
        "x": 6,
        "y": 15,
        "heat": 7.92
      }
    ],
    "updated": "2026-06-18T13:22:55",
    "simulation": {
      "scenario": "checkout_relocate",
      "shift_cols": 3,
      "peak_before": 7.922993183135986,
      "peak_after": 7.922993183135986,
      "hint": "右移收银台可能缓解入口侧堆积"
    }
  },
  "multiview": {
    "grid_size": 32,
    "hotspots": [
      {
        "gx": 14,
        "gy": 8,
        "v": 1.07
      },
      {
        "gx": 12,
        "gy": 12,
        "v": 1.306
      },
      {
        "gx": 8,
        "gy": 30,
        "v": 0.861
      }
    ],
    "cam_count": 2
  },
  "attribution": {
    "insights": [],
    "samples": 30
  },
  "active_learning": [
    {
      "path": "/Users/james/Project/jiance/store/analytics_logs/active_learning/Cam_231_Counter_20260618_131843_064327.jpg",
      "cam": "Cam_231_Counter",
      "reason": "low_conf",
      "conf": 0.33712542057037354,
      "ts": "2026-06-18T13:18:43"
    },
    {
      "path": "/Users/james/Project/jiance/store/analytics_logs/active_learning/Cam_231_Counter_20260618_131802_658652.jpg",
      "cam": "Cam_231_Counter",
      "reason": "low_conf",
      "conf": 0.3653118312358856,
      "ts": "2026-06-18T13:18:02"
    },
    {
      "path": "/Users/james/Project/jiance/store/analytics_logs/active_learning/Cam_104_Specialty_20260618_131759_116779.jpg",
      "cam": "Cam_104_Specialty",
      "reason": "low_conf",
      "conf": 0.4431167542934418,
      "ts": "2026-06-18T13:17:59"
    },
    {
      "path": "/Users/james/Project/jiance/store/analytics_logs/active_learning/Cam_231_Counter_20260618_131757_612378.jpg",
      "cam": "Cam_231_Counter",
      "reason": "low_conf",
      "conf": 0.2550995647907257,
      "ts": "2026-06-18T13:17:57"
    },
    {
      "path": "/Users/james/Project/jiance/store/analytics_logs/active_learning/Cam_231_Counter_20260618_131756_027209.jpg",
      "cam": "Cam_231_Counter",
      "reason": "low_conf",
      "conf": 0.3332923352718353,
      "ts": "2026-06-18T13:17:56"
    },
    {
      "path": "/Users/james/Project/jiance/store/analytics_logs/active_learning/Cam_231_Counter_20260618_131754_645150.jpg",
      "cam": "Cam_231_Counter",
      "reason": "low_conf",
      "conf": 0.3872157037258148,
      "ts": "2026-06-18T13:17:54"
    },
    {
      "path": "/Users/james/Project/jiance/store/analytics_logs/active_learning/Cam_231_Counter_20260618_131753_489743.jpg",
      "cam": "Cam_231_Counter",
      "reason": "low_conf",
      "conf": 0.3766990303993225,
      "ts": "2026-06-18T13:17:53"
    },
    {
      "path": "/Users/james/Project/jiance/store/analytics_logs/active_learning/Cam_104_Specialty_20260618_131751_907683.jpg",
      "cam": "Cam_104_Specialty",
      "reason": "low_conf",
      "conf": 0.3232681453227997,
      "ts": "2026-06-18T13:17:51"
    }
  ]
}